Metadata-Version: 2.1
Name: firebase-dynamic-link-generator
Version: 1.0.1
Summary: Python client for Firebase Dynamic Links API
Home-page: https://github.com/zammy395/firebase-dynamic-link-generator
Author: Sufiyan Shaikh
Author-email: sufiyan8shaikh@gmail.com	
Maintainer: Sufiyan Shaikh
Maintainer-email: sufiyan8shaikh@gmail.com
License: UNKNOWN
Project-URL: Bug Reports, https://github.com/zammy395/firebase-dynamic-link-generator/issues
Project-URL: Source, https://github.com/zammy395/firebase-dynamic-link-generator
Keywords: firebase,dynamic links,url shortener,dynamic link custom suffix
Platform: UNKNOWN
Classifier: Programming Language :: Python :: 3
Classifier: License :: OSI Approved :: MIT License
Classifier: Operating System :: POSIX :: Linux
Classifier: Development Status :: 5 - Production/Stable
Classifier: Intended Audience :: Developers
License-File: LICENSE
